print_separator/__init__.py
print_separator-0.1.3.dist-info/METADATA
print_separator-0.1.3.dist-info/WHEEL
print_separator-0.1.3.dist-info/licenses/LICENSE
print_separator-0.1.3.dist-info/RECORD
